tidyfile/__init__.py
tidyfile/main.py
tidyfile/modules/file_classifier.py
tidyfile/modules/file_exporter.py
tidyfile/modules/file_organiser.py
tidyfile/utils/logger_setup.py
tidyfile-0.1.post1.dist-info/METADATA
tidyfile-0.1.post1.dist-info/WHEEL
tidyfile-0.1.post1.dist-info/entry_points.txt
tidyfile-0.1.post1.dist-info/licenses/LICENSE
tidyfile-0.1.post1.dist-info/RECORD
