Metadata-Version: 2.4
Name: tidyfile
Version: 0.1.post1
Summary: A CLI tool to sort your files into organized directories.
Project-URL: Repository, https://github.com/heshinth/tidyfile.git
Project-URL: Issues, https://github.com/heshinth/tidyfile/issues
Author-email: Heshinth <heshinth@gmail.com>
License:                     GNU GENERAL PUBLIC LICENSE
License-File: LICENSE
Keywords: CLI,automation,directory,file,file management,file sorter,organization,organizer,productivity,utilities
Requires-Python: >=3.12
Requires-Dist: typer>=0.15.1
